neuro_ix_tools/__init__.py
neuro_ix_tools/bids.py
neuro_ix_tools/config.py
neuro_ix_tools/processing/__init__.py
neuro_ix_tools/processing/apptainer.py
neuro_ix_tools/processing/base_cmd.py
neuro_ix_tools/processing/freesurfer.py
neuro_ix_tools/processing/slurm.py
neuro_ix_tools-0.0.8.dist-info/METADATA
neuro_ix_tools-0.0.8.dist-info/WHEEL
neuro_ix_tools-0.0.8.dist-info/entry_points.txt
neuro_ix_tools-0.0.8.dist-info/licenses/LICENSE
neuro_ix_tools-0.0.8.dist-info/RECORD
