Metadata-Version: 2.4
Name: neuro-ix-tools
Version: 0.0.8
Summary: CLI and utils for the Neuro-iX lab
Project-URL: Repository, https://github.com/chbricout/neuro-ix-tools
Author-email: Charles Bricout <bricout.charles@outlook.com>
License-Expression: MIT
License-File: LICENSE
Requires-Python: >=3.11
Requires-Dist: click==8.1.8
Requires-Dist: dotenv==0.9.9
Requires-Dist: platformdirs==4.3.7
Requires-Dist: rich==14.0.0
Requires-Dist: simple-slurm==0.2.7
Provides-Extra: test
Requires-Dist: mypy==1.15.0; extra == 'test'
Requires-Dist: pre-commit==4.2.0; extra == 'test'
Requires-Dist: pydocstyle==6.3.0; extra == 'test'
Requires-Dist: pylint==3.3.6; extra == 'test'
Requires-Dist: pytest-cov==6.1.1; extra == 'test'
Requires-Dist: pytest==8.3.5; extra == 'test'
Requires-Dist: ruff==0.11.7; extra == 'test'
Requires-Dist: ssort==0.14.0; extra == 'test'
